taskflows/__init__.py
taskflows/admin/__init__.py
taskflows/admin/api.py
taskflows/admin/auth.py
taskflows/admin/cli.py
taskflows/admin/core.py
taskflows/admin/environments.py
taskflows/admin/models.py
taskflows/admin/security.py
taskflows/admin/utils.py
taskflows/alerts/README.md
taskflows/alerts/__init__.py
taskflows/alerts/alerts.py
taskflows/alerts/components.py
taskflows/alerts/discord.py
taskflows/alerts/emails.py
taskflows/alerts/report.py
taskflows/alerts/slack.py
taskflows/alerts/utils.py
taskflows/common.py
taskflows/constants.py
taskflows/constraints.py
taskflows/dashboard.py
taskflows/db.py
taskflows/docker.py
taskflows/dynamic_imports.py
taskflows/entrypoints.py
taskflows/exceptions.py
taskflows/exec.py
taskflows/files/README.md
taskflows/files/__init__.py
taskflows/files/core.py
taskflows/files/extensions.py
taskflows/files/gdrive.py
taskflows/files/gsheets.py
taskflows/files/s3.py
taskflows/files/utils.py
taskflows/loggers/__init__.py
taskflows/loggers/basic.py
taskflows/loggers/structured.py
taskflows/metrics.py
taskflows/middleware/__init__.py
taskflows/middleware/prometheus_middleware.py
taskflows/schedule.py
taskflows/security_validation.py
taskflows/service.py
taskflows/tasks.py
taskflows-0.19.0.dist-info/METADATA
taskflows-0.19.0.dist-info/WHEEL
taskflows-0.19.0.dist-info/entry_points.txt
taskflows-0.19.0.dist-info/RECORD
