Metadata-Version: 2.4
Name: taskflows
Version: 0.19.0
Summary: 
Author: Dan Kelleher
Author-email: kelleherjdan@gmail.com
Requires-Python: >=3.12,<4.0
Classifier: Programming Language :: Python :: 3
Classifier: Programming Language :: Python :: 3.12
Classifier: Programming Language :: Python :: 3.13
Classifier: Programming Language :: Python :: 3.14
Requires-Dist: aiohttp (>=3.12.15,<4.0.0)
Requires-Dist: aiosmtplib (>=4.0.1,<5.0.0)
Requires-Dist: aiosqlite (>=0.21.0,<0.22.0)
Requires-Dist: anyio (>=4.0.0,<5.0.0)
Requires-Dist: async-lru (>=2.0.5,<3.0.0)
Requires-Dist: asyncpg (>=0.30.0,<0.31.0)
Requires-Dist: boto3 (>=1.40.40,<2.0.0)
Requires-Dist: click (>=8.2.1,<9.0.0)
Requires-Dist: cloudpickle (>=3.1.1,<4.0.0)
Requires-Dist: dbus-next (>=0.2.3,<0.3.0)
Requires-Dist: docker (>=7.1.0,<8.0.0)
Requires-Dist: dominate (>=2.9.1,<3.0.0)
Requires-Dist: duckdb (>=1.4.0,<2.0.0)
Requires-Dist: emoji (>=2.14.1,<3.0.0)
Requires-Dist: fastapi (>=0.116.1,<0.117.0)
Requires-Dist: grafanalib (>=0.7.1,<0.8.0)
Requires-Dist: gspread (>=6.2.1,<7.0.0)
Requires-Dist: imgkit (>=1.2.3,<2.0.0)
Requires-Dist: loguru (>=0.7.3,<0.8.0)
Requires-Dist: pandas (>=2.3.2,<3.0.0)
Requires-Dist: passlib[bcrypt] (>=1.7.4,<2.0.0)
Requires-Dist: prettytable (>=3.16.0,<4.0.0)
Requires-Dist: prometheus-client (>=0.19.0,<1.0.0)
Requires-Dist: pyarrow (>=21.0.0,<22.0.0)
Requires-Dist: pydantic (>=2.11.9,<3.0.0)
Requires-Dist: pydantic-settings (>=2.11.0,<3.0.0)
Requires-Dist: pydrive (>=1.3.1,<2.0.0)
Requires-Dist: pyjwt (>=2.8.0,<3.0.0)
Requires-Dist: requests (>=2.32.5,<3.0.0)
Requires-Dist: rich (>=14.1.0,<15.0.0)
Requires-Dist: slack-sdk (>=3.36.0,<4.0.0)
Requires-Dist: sqlalchemy (>=2.0.43,<3.0.0)
Requires-Dist: structlog (>=25.4.0,<26.0.0)
Requires-Dist: textdistance (>=4.6.3,<5.0.0)
Requires-Dist: toolz (>=1.0.0,<2.0.0)
Requires-Dist: uvicorn (>=0.35.0,<0.36.0)
Requires-Dist: xxhash (>=3.5.0,<4.0.0)
